Metadata-Version: 2.4
Name: hhg9
Version: 0.1.0a3
Summary: Hierarchical hexagonal grid on an octahedral earth projection
Author: Ben Griffin
License: 
Project-URL: Homepage, https://github.com/MrBenGriffin/hex9
Project-URL: Documentation, https://github.com/MrBenGriffin/hex9/blob/main/README.md
Project-URL: Repository, https://github.com/MrBenGriffin/hex9
Project-URL: Issues, https://github.com/MrBenGriffin/hex9/issues
Project-URL: Changelog, https://github.com/MrBenGriffin/hex9/releases
Classifier: Development Status :: 3 - Alpha
Classifier: Intended Audience :: Science/Research
Classifier: License :: OSI Approved :: Apache Software License
Classifier: Programming Language :: Python :: 3
Classifier: Programming Language :: Python :: 3.10
Classifier: Programming Language :: Python :: 3.11
Classifier: Programming Language :: Python :: 3.12
Classifier: Topic :: Scientific/Engineering :: GIS
Requires-Python: >=3.10
License-File: LICENSE
Requires-Dist: numpy>=2.0.0
Requires-Dist: scipy>=1.11.0
Requires-Dist: pyproj>=3.0.0
Requires-Dist: geographiclib>=2.0
Provides-Extra: dev
Requires-Dist: pytest; extra == "dev"
Dynamic: license-file
